{
    "uiList": [
        {
            "name": "tip",
            "info":" tip系统提示组件"
        },
        {
            "name": "modal",
            "info":"弹出框组件"
        },
        {
            "name":"uploader",
            "info":"图片上传组件"
        },
        {
          "name":"browser",
            "info":"浏览器检测组件"
        },
        {
            "name":"MDEditor",
            "info":"md编辑器组件"
        },
        {
            "name":"ws",
            "info":"WebScoket通信组件"
        }
    ]
}